cldfzenodo/__init__.py
cldfzenodo/api.py
cldfzenodo/oai.py
cldfzenodo/record.py
cldfzenodo/search.py
cldfzenodo/commands/__init__.py
cldfzenodo/commands/download.py
cldfzenodo-2.2.1.dist-info/LICENSE
cldfzenodo-2.2.1.dist-info/METADATA
cldfzenodo-2.2.1.dist-info/WHEEL
cldfzenodo-2.2.1.dist-info/entry_points.txt
cldfzenodo-2.2.1.dist-info/top_level.txt
cldfzenodo-2.2.1.dist-info/RECORD
