Metadata-Version: 2.1
Name: cldfzenodo
Version: 2.2.1
Summary: Functionality to retrieve CLDF datasets deposited on Zenodo
Home-page: https://github.com/cldf/cldfzenodo
Author: Robert Forkel
Author-email: dlce.rdm@eva.mpg.de
License: Apache 2.0
Project-URL: Bug Tracker, https://github.com/cldf/cldfzenodo/issues
Keywords: linguistics
Platform: any
Classifier: Development Status :: 5 - Production/Stable
Classifier: Intended Audience :: Developers
Classifier: Intended Audience :: Science/Research
Classifier: Natural Language :: English
Classifier: Operating System :: OS Independent
Classifier: Programming Language :: Python :: 3
Classifier: Programming Language :: Python :: 3.8
Classifier: Programming Language :: Python :: 3.9
Classifier: Programming Language :: Python :: 3.10
Classifier: Programming Language :: Python :: 3.11
Classifier: Programming Language :: Python :: 3.12
Classifier: Programming Language :: Python :: 3.13
Classifier: Programming Language :: Python :: 3.14
Classifier: Programming Language :: Python :: Implementation :: CPython
Classifier: Programming Language :: Python :: Implementation :: PyPy
Classifier: License :: OSI Approved :: Apache Software License
Requires-Python: >=3.8
License-File: LICENSE
Requires-Dist: clldutils
Requires-Dist: pycldf>=1.30.0
Requires-Dist: nameparser
Requires-Dist: attrs
Provides-Extra: cli
Requires-Dist: cldfbench; extra == "cli"
Provides-Extra: dev
Requires-Dist: flake8; extra == "dev"
Requires-Dist: wheel; extra == "dev"
Requires-Dist: build; extra == "dev"
Requires-Dist: twine; extra == "dev"
Provides-Extra: test
Requires-Dist: cldfbench; extra == "test"
Requires-Dist: pytest>=5; extra == "test"
Requires-Dist: pytest-mock; extra == "test"
Requires-Dist: pytest-cov; extra == "test"
Requires-Dist: coverage>=4.2; extra == "test"
